Metadata-Version: 2.1
Name: beziers
Version: 0.4.0
Summary: Bezier curve manipulation library
Home-page: https://github.com/simoncozens/beziers.py
Author: Simon Cozens
Author-email: simon@simon-cozens.org
License: MIT
Platform: UNKNOWN
Classifier: Programming Language :: Python
Classifier: Programming Language :: Python :: 2
Classifier: Programming Language :: Python :: 3
Classifier: License :: OSI Approved :: MIT License
Classifier: Development Status :: 4 - Beta
License-File: LICENSE
